{
  "streams": [
    {
      "title": "patch vs put",
      "description": "patch edit some records but put edit all record",
      "userId": "100955947713643698019",
      "id": 11
    },
    {
      "title": "History programmatic  navigation",
      "description": "this will back you to the streams screen",
      "userId": "100955947713643698019",
      "id": 12
    },
    {
      "title": "Create new streams",
      "description": "i have created new stream",
      "userId": "100955947713643698019",
      "id": 14
    },
    {
      "title": "Made stream",
      "description": "this new stream ",
      "userId": "100955947713643698019",
      "id": 15
    }
  ]
}